CHANGES.txt
COPYRIGHT.txt
LICENSE.txt
README.txt
buildout.cfg
setup.py
versions.cfg
bootstrap/bootstrap.py
src/megrok/__init__.py
src/megrok.login.egg-info/PKG-INFO
src/megrok.login.egg-info/SOURCES.txt
src/megrok.login.egg-info/dependency_links.txt
src/megrok.login.egg-info/namespace_packages.txt
src/megrok.login.egg-info/not-zip-safe
src/megrok.login.egg-info/requires.txt
src/megrok.login.egg-info/top_level.txt
src/megrok/login/README.txt
src/megrok/login/__init__.py
src/megrok/login/authplugins.py
src/megrok/login/component.py
src/megrok/login/configure.zcml
src/megrok/login/ftesting.zcml
src/megrok/login/grokker.py
src/megrok/login/loginform.pt
src/megrok/login/loginform.py
src/megrok/login/loginpage.zcml
src/megrok/login/meta.zcml
src/megrok/login/tests/__init__.py
src/megrok/login/tests/autoregister.py
src/megrok/login/tests/customlogin.py
src/megrok/login/tests/custompausetup.py
src/megrok/login/tests/simple.py
src/megrok/login/tests/strict.py
src/megrok/login/tests/test_login.py
src/megrok/login/tests/unset.py
src/megrok/login/tests/customlogin_templates/login.pt