Metadata-Version: 1.0
Name: megrok.login
Version: 0.4
Summary: Providing login screens for your Grok apps made easy.
Home-page: http://pypi.python.org/pypi/megrok.login
Author: Uli Fouquet and the Zope Community
Author-email: uli@gnufix.de
License: ZPL 2.1
Keywords: zope3 zope login grok security PAU
Platform: UNKNOWN
Classifier: Development Status :: 3 - Alpha
Classifier: Environment :: Web Environment
Classifier: Intended Audience :: Developers
Classifier: License :: OSI Approved :: Zope Public License
Classifier: Programming Language :: Python
Classifier: Operating System :: OS Independent
Classifier: Framework :: Zope3
